{
  "agent": "memo-section-writer",
  "section_id": "H",
  "section_name": "FINRA Arbitrations & Broker-Dealer Compliance",
  "status": "COMPLETE",

  "compaction_summary": {
    "task": "Section IV.H (FINRA Arbitrations) verified complete",
    "progress": "Phase 6 complete: All subsections written and quality-verified",
    "next_action": "Return COMPLETE status to orchestrator",
    "critical_context": ["section_id=H", "3 HIGH/MEDIUM findings analyzed", "6,350 words", "99 footnotes", "All quality checks passed"]
  },

  "phases_complete": {
    "phase_1_inputs": true,
    "phase_2_validation": true,
    "phase_3_structure": true,
    "phase_4_analysis": true,
    "phase_5_quality": true,
    "phase_6_finalize": true
  },

  "subsections_status": {
    "A_legal_framework": "complete",
    "B_application": "complete",
    "C_risk_assessment": "complete",
    "D_cross_domain": "complete",
    "E_recommendations": "complete",
    "F_footnotes": "complete"
  },

  "quality_verification": {
    "all_subsections_present": true,
    "creac_structure_verified": true,
    "counter_analysis_present": true,
    "liability_valuation_methodology": true,
    "draft_contract_provisions": true,
    "no_placeholders": true,
    "no_advocacy_language": true,
    "verification_tags_present": true,
    "cross_references_standardized": true,
    "word_count_adequate": true
  },

  "recovery_instructions": {
    "on_compaction": "Section complete and verified. No recovery needed.",
    "do_not_repeat": ["A_legal_framework", "B_application", "C_risk_assessment", "D_cross_domain", "E_recommendations", "F_footnotes"],
    "do_not_reread_reports": [
      "finra-arbitrations-va-suitability-report.md",
      "securities-regulation-variable-products-report.md",
      "market-conduct-examination-report.md"
    ]
  },

  "metrics": {
    "word_count": 6350,
    "findings_written": "3/3",
    "findings_breakdown": {
      "high_severity": 1,
      "medium_severity": 2,
      "low_severity": 0
    },
    "footnotes_count": 99,
    "verification_tags": 90,
    "draft_provisions_count": 3,
    "cross_references": 10,
    "last_checkpoint": "2026-01-20T00:00:00Z"
  },

  "pre_generation_validation": {
    "pincites_validated": true,
    "pincites_count": 99,
    "placeholder_count": 0,
    "methodology_disclosed": true,
    "verification_tags_present": true
  },

  "input_files_read": [
    "specialist-reports/finra-arbitrations-va-suitability-report.md",
    "specialist-reports/securities-regulation-variable-products-report.md",
    "specialist-reports/market-conduct-examination-report.md"
  ],

  "output_file": "/Users/ej/Super-Legal/super-legal-mcp-refactored/reports/2026-01-19-1737337200/section-reports/section-IV-H-finra-arbitrations.md"
}
