{
  "agent": "memo-section-writer",
  "section_id": "H",
  "section_name": "Investment Portfolio Risk and Asset-Liability Management",
  "status": "COMPLETE",

  "compaction_summary": {
    "task": "Write section IV-H (Investment Portfolio Risk) from specialist reports",
    "progress": "COMPLETE - All phases finished",
    "next_action": "None - section complete",
    "critical_context": ["section_id=H", "5 findings analyzed with CREAC", "163 footnotes with verification tags"]
  },

  "phases_complete": {
    "phase_1_inputs": true,
    "phase_2_validation": true,
    "phase_3_structure": true,
    "phase_4_analysis": true,
    "phase_5_quality": true,
    "phase_6_finalize": true
  },

  "subsections_status": {
    "A_legal_framework": "complete",
    "B_application": "complete",
    "C_risk_assessment": "complete",
    "D_cross_domain": "complete",
    "E_recommendations": "complete",
    "F_footnotes": "complete"
  },

  "recovery_instructions": {
    "on_compaction": "Section complete - no recovery needed",
    "do_not_repeat": ["A_legal_framework", "B_application", "C_risk_assessment", "D_cross_domain", "E_recommendations", "F_footnotes"],
    "do_not_reread_reports": ["investment-portfolio-risk-report.md", "fact-registry.md"]
  },

  "metrics": {
    "word_count": 13500,
    "findings_written": "5/5",
    "footnotes_count": 163,
    "last_checkpoint": "2026-01-21T14:30:00Z"
  },

  "input_files_read": [
    "specialist-reports/investment-portfolio-risk-report.md",
    "review-outputs/fact-registry.md"
  ],

  "output_file": "/Users/ej/Super-Legal/super-legal-mcp-refactored/reports/2026-01-21-1737490800/section-reports/section-IV-H-investment-portfolio.md"
}
